nimble_tk/__init__.py
nimble_tk/analytics/__init__.py
nimble_tk/analytics/pandas_utils.py
nimble_tk/analytics/string_utils.py
nimble_tk/common/__init__.py
nimble_tk/common/files.py
nimble_tk/common/general_utils.py
nimble_tk/common/logger.py
nimble_tk/linux/__init__.py
nimble_tk/notebook/__init__.py
nimble_tk/notebook/display.py
nimble_tk/tasks/__init__
nimble_tk/tasks/concurrent.py
nimble_tk/tasks/schedulers.py
nimble_tk-1.0.3.dist-info/METADATA
nimble_tk-1.0.3.dist-info/WHEEL
nimble_tk-1.0.3.dist-info/licenses/LICENSE
nimble_tk-1.0.3.dist-info/RECORD
